enlightenme/__init__.py
enlightenme/__version__.py
enlightenme/enlightenme.py
enlightenme/utils.py
enlightenme/commands/__init__.py
enlightenme/commands/source_command.py
enlightenme/news/__init__.py
enlightenme/news/news.py
enlightenme/news/news_formatters.py
enlightenme/news/news_manager.py
enlightenme/news/news_output.py
enlightenme/sources/__init__.py
enlightenme/sources/all_source.py
enlightenme/sources/hacker_news_source.py
enlightenme/sources/reddit_source.py
enlightenme-0.1.0.dist-info/DESCRIPTION.rst
enlightenme-0.1.0.dist-info/METADATA
enlightenme-0.1.0.dist-info/RECORD
enlightenme-0.1.0.dist-info/WHEEL
enlightenme-0.1.0.dist-info/entry_points.txt
enlightenme-0.1.0.dist-info/metadata.json
enlightenme-0.1.0.dist-info/top_level.txt
