Metadata-Version: 2.0
Name: enlightenme
Version: 0.1.0
Summary: LI for curating and reading news/updates.
Home-page: https://github.com/singhgarima/enlightenme
Author: Garima Singh
Author-email: igarimasingh+enlightenme@gmail.com
License: MIT License
Platform: UNKNOWN
Classifier: Development Status :: 3 - Alpha
Classifier: Intended Audience :: Developers
Classifier: Natural Language :: English
Classifier: License :: OSI Approved :: MIT License
Classifier: Programming Language :: Python
Classifier: Programming Language :: Python :: 3.5
Classifier: Programming Language :: Python :: 3.6
Classifier: Programming Language :: Python :: 3.7
Requires-Dist: certifi (==2018.8.24)
Requires-Dist: chardet (==3.0.4)
Requires-Dist: click (==6.7)
Requires-Dist: idna (==2.7)
Requires-Dist: praw (==6.0.0)
Requires-Dist: prawcore (==1.0.0)
Requires-Dist: requests (==2.19.1)
Requires-Dist: update-checker (==0.16)
Requires-Dist: urllib3 (==1.23)
